femtocrux/ENV_REQUIREMENTS.sh
femtocrux/PY_REQUIREMENTS
femtocrux/VERSION
femtocrux/__init__.py
femtocrux/version.py
femtocrux/client/__init__.py
femtocrux/client/client.py
femtocrux/grpc/__init__.py
femtocrux/grpc/compiler_service_pb2.py
femtocrux/grpc/compiler_service_pb2_grpc.py
femtocrux/server/__init__.py
femtocrux/server/compiler_frontend.py
femtocrux/server/exceptions.py
femtocrux/server/healthcheck.py
femtocrux/server/server.py
femtocrux/util/__init__.py
femtocrux/util/utils.py
femtocrux-3.2.2.dist-info/licenses/LICENSE
femtocrux-3.2.2.dist-info/METADATA
femtocrux-3.2.2.dist-info/WHEEL
femtocrux-3.2.2.dist-info/top_level.txt
femtocrux-3.2.2.dist-info/RECORD
