Metadata-Version: 2.4
Name: femtocrux
Version: 3.2.2
Summary: Femtosense Compiler
Home-page: https://github.com/femtosense/femtocrux
Author: Femtosense
Author-email: info@femtosense.ai
Project-URL: Source, https://github.com/femtosense/femtocrux
Classifier: Development Status :: 3 - Alpha
Classifier: Intended Audience :: Developers
Classifier: Programming Language :: Python :: 3.10
Classifier: Programming Language :: Python :: 3 :: Only
Classifier: Operating System :: OS Independent
Requires-Python: >=3.10
License-File: LICENSE
Requires-Dist: Cython
Requires-Dist: docker
Requires-Dist: fmot<4.0.0,>=1.9.2
Requires-Dist: grpcio>=1.64.1
Requires-Dist: grpcio-tools>=1.64.1
Requires-Dist: numpy>=1.18.0
Requires-Dist: protobuf
Requires-Dist: passlib
Requires-Dist: requests<2.29.0
Requires-Dist: urllib3<2.0.0,>=1.26.0
Dynamic: author
Dynamic: author-email
Dynamic: classifier
Dynamic: description
Dynamic: description-content-type
Dynamic: home-page
Dynamic: license-file
Dynamic: project-url
Dynamic: requires-dist
Dynamic: requires-python
Dynamic: summary
